doublediff/__init__.py
doublediff/_version.py
doublediff/data.py
doublediff/utils.py
doublediff/_data/__init__.py
doublediff/_data/ehec_data.pkl.gz
doublediff/_data/mpdta_long.pkl.gz
doublediff/_data/nsw_long.pkl.gz
doublediff/did/README.md
doublediff/did/__init__.py
doublediff/did/aggte.py
doublediff/did/aggte_obj.py
doublediff/did/att_gt.py
doublediff/did/compute_aggte.py
doublediff/did/compute_att_gt.py
doublediff/did/mboot.py
doublediff/did/multiperiod_obj.py
doublediff/did/preprocess_did.py
doublediff/did/plots/__init__.py
doublediff/did/plots/core.py
doublediff/did/plots/methods.py
doublediff/did/preprocess/__init__.py
doublediff/did/preprocess/builders.py
doublediff/did/preprocess/constants.py
doublediff/did/preprocess/models.py
doublediff/did/preprocess/tensors.py
doublediff/did/preprocess/transformers.py
doublediff/did/preprocess/validators.py
doublediff/did2s/README.md
doublediff/did2s/__init__.py
doublediff/didbacon/README.md
doublediff/didbacon/__init__.py
doublediff/didcomp/README.md
doublediff/didcomp/__init__.py
doublediff/didcont/README.md
doublediff/didcont/__init__.py
doublediff/didhonest/README.md
doublediff/didhonest/__init__.py
doublediff/didhonest/arp_no_nuisance.py
doublediff/didhonest/arp_nuisance.py
doublediff/didhonest/bounds.py
doublediff/didhonest/conditional.py
doublediff/didhonest/fixed_length_ci.py
doublediff/didhonest/honest_did.py
doublediff/didhonest/numba.py
doublediff/didhonest/sensitivity.py
doublediff/didhonest/utils.py
doublediff/didhonest/wrappers.py
doublediff/didhonest/delta/__init__.py
doublediff/didhonest/delta/base.py
doublediff/didhonest/delta/rm/__init__.py
doublediff/didhonest/delta/rm/rm.py
doublediff/didhonest/delta/rm/rmb.py
doublediff/didhonest/delta/rm/rmm.py
doublediff/didhonest/delta/sd/__init__.py
doublediff/didhonest/delta/sd/sd.py
doublediff/didhonest/delta/sd/sdb.py
doublediff/didhonest/delta/sd/sdm.py
doublediff/didhonest/delta/sdrm/__init__.py
doublediff/didhonest/delta/sdrm/sdrm.py
doublediff-0.0.1.dist-info/licenses/LICENSE
doublediff-0.0.1.dist-info/WHEEL
doublediff-0.0.1.dist-info/METADATA
doublediff-0.0.1.dist-info/RECORD
